azure/ai/contentsafety/__init__.py
azure/ai/contentsafety/_client.py
azure/ai/contentsafety/_configuration.py
azure/ai/contentsafety/_model_base.py
azure/ai/contentsafety/_patch.py
azure/ai/contentsafety/_serialization.py
azure/ai/contentsafety/_vendor.py
azure/ai/contentsafety/_version.py
azure/ai/contentsafety/py.typed
azure/ai/contentsafety/_operations/__init__.py
azure/ai/contentsafety/_operations/_operations.py
azure/ai/contentsafety/_operations/_patch.py
azure/ai/contentsafety/aio/__init__.py
azure/ai/contentsafety/aio/_client.py
azure/ai/contentsafety/aio/_configuration.py
azure/ai/contentsafety/aio/_patch.py
azure/ai/contentsafety/aio/_vendor.py
azure/ai/contentsafety/aio/_operations/__init__.py
azure/ai/contentsafety/aio/_operations/_operations.py
azure/ai/contentsafety/aio/_operations/_patch.py
azure/ai/contentsafety/models/__init__.py
azure/ai/contentsafety/models/_enums.py
azure/ai/contentsafety/models/_models.py
azure/ai/contentsafety/models/_patch.py
azure_ai_contentsafety-1.0.0.dist-info/LICENSE
azure_ai_contentsafety-1.0.0.dist-info/METADATA
azure_ai_contentsafety-1.0.0.dist-info/WHEEL
azure_ai_contentsafety-1.0.0.dist-info/top_level.txt
azure_ai_contentsafety-1.0.0.dist-info/RECORD
